6/VHDL/uartTxTest/txTest/chacha_qr.vhdl
library ieee;
use ieee.std_logic_1164.all;
use ieee.numeric_std.all;

entity chacha_qr is
    port 
    (
        clk : in    std_ulogic;

        a   : in    unsigned(31 downto 0);
        b   : in    unsigned(31 downto 0);
        c   : in    unsigned(31 downto 0);
        d   : in    unsigned(31 downto 0);

        a2  : out   unsigned(31 downto 0);
        b2  : out   unsigned(31 downto 0);
        c2  : out   unsigned(31 downto 0);
        d2  : out   unsigned(31 downto 0);

        done: out   unsigned(0 downto 0)
    );
end chacha_qr;

architecture behave of chacha_qr is
signal a2Signal: unsigned(31 downto 0);
signal b2Signal: unsigned(31 downto 0);
signal c2Signal: unsigned(31 downto 0);
signal d2Signal: unsigned(31 downto 0);

begin
    a2 <= a2Signal;
    b2 <= b2Signal;
    c2 <= c2Signal;
    d2 <= d2Signal;

    process (clk)
        variable state: unsigned(1 downto 0) := "00";
        variable index: unsigned(4 downto 0) := "00000";
    begin
        if (rising_edge(clk)) then
            if (state = "00") then
                a2Signal <= a + b;
                b2Signal <= b;
                c2Signal <= c;
                d2Signal <= (d xor a2Signal) sll 16;

                done <= "0";
                state := "01";

            elsif (state = "01") then
                --c += d; b ^= c; b <<<= 12;
                c2Signal <= c2Signal + d2Signal;
                b2Signal <= (b2Signal xor c2Signal) sll 12;
                state := "10";

            elsif (state = "10") then
                --a += b; d ^= a; d <<<= 8;
                a2Signal <= a2Signal + b2Signal;
                d2Signal <= (d2Signal xor a2Signal) sll 8;
                state := "11";

            else
                --c += d; b ^= c; b <<<= 7;
                c2Signal <= c2Signal + d2Signal;
                b2Signal <= (b2Signal xor c2Signal) sll 7;

                if (index = "10100" and state = "11") then
                    done <= "1";
                    index := "00000";
    
                else
                    index := index + 1;
                end if;

                state := "00";
            end if;
        end if;
    end process;
end behave;

6/VHDL/uartTxTest/txTest/uart8n1_tx.vhdl
library ieee;
use ieee.std_logic_1164.all;
use ieee.numeric_std.all;

entity uart8n1_tx is
    port 
    (
        clk     : in    std_ulogic;
        en      : in    unsigned(0 downto 0);
        txByte  : in    unsigned(7 downto 0);
        sendData: in    unsigned(0 downto 0);

        isIdle  : out   unsigned(0 downto 0);
        txDone  : out   unsigned(0 downto 0);
        tx      : out   unsigned(0 downto 0)
    );

subtype st_logicBit is std_ulogic;
subtype st_bit is unsigned(0 downto 0);
subtype st_byte is unsigned(7 downto 0);
subtype state_t is unsigned(1 downto 0);
end uart8n1_tx;

architecture behave of uart8n1_tx is
signal txBit: st_bit    := "1";
--signal bufTx: st_byte   := "00000000";

signal isidleSignal: unsigned(0 downto 0) := "1";
signal isDoneSignal: unsigned(0 downto 0) := "1";

begin
    tx <= txBit;
    isIdle <= isidleSignal;
    txDone <= isDoneSignal;

    --bufTx <= txByte;

    process (clk)
    
    constant StateIdle      : state_t   := "00";
    constant StateStartTx   : state_t   := "01";
    constant StateTxing     : state_t   := "10";
    constant StateTxDone    : state_t   := "11";

    variable state          : state_t   := StateIdle;
    variable bufTx: st_byte   := "00000000";
    variable bitsSent       : st_byte   := "00000000";
    --variable txBit          : _bit    := "1";*/

    begin
        if (rising_edge(clk) and en = "1") then
            if (state = StateIdle) then
                isidleSignal <= "1";
                if (sendData = "1" and state = StateIdle) then
                    state := StateStartTx;
                    bufTx := txByte;
                    isDoneSignal <= "0";

                elsif (state = StateIdle) then
                    txBit <= "1";
                    isDoneSignal <= "0";
                end if;

            elsif (state = StateStartTx) then
                isidleSignal <= "0";
                if (state = StateStartTx) then
                    txBit <= "0";
                    state := StateTxing;
                end if;

            elsif (state = StateTxing) then
                isidleSignal <= "0";
                if (state = StateTxing and bitsSent < to_unsigned(8, 8)) then
                    txBit <= bufTx(0 downto 0);
                    bufTx := shift_right(bufTx, 1);
                    bitsSent := bitsSent + 1;
            
                elsif (state = StateTxing) then
                    txBit <= "1";
                    bitsSent := "00000000";
                    state := StateTxDone;
                end if;

            elsif (state = StateTxDone) then
                isidleSignal <= "0";
                if (state = StateTxDone) then
                    isDoneSignal <= "1";
                    state := StateIdle;
                end if;
            end if;
        end if;

    end process;
end behave;

6/VHDL/uartTxTest/txTest/uart8n1_tx2_tb.vhdl
library ieee;
use ieee.std_logic_1164.all;
use ieee.numeric_std.all;

entity uart8n1_tx2_tb is
    port 
    (
        --hwclk     : in      std_ulogic;
        ledGreen  : out     unsigned(0 downto 0);
        led0      : out     unsigned(0 downto 0);
        ftdi_tx   : out     unsigned(0 downto 0)
    );
end uart8n1_tx2_tb;

architecture test of uart8n1_tx2_tb is
    component uart8n1_tx
        port 
        (
            clk     : in    std_ulogic;
            en      : in    unsigned(0 downto 0);
            txByte  : in    unsigned(7 downto 0);
            sendData: in    unsigned(0 downto 0);
    
            isIdle  : out   unsigned(0 downto 0);
            txDone  : out   unsigned(0 downto 0);
            tx      : out   unsigned(0 downto 0)
        );
    end component;

    component chacha_qr
        port 
        (
            clk : in    std_ulogic;
    
            a   : in    unsigned(31 downto 0);
            b   : in    unsigned(31 downto 0);
            c   : in    unsigned(31 downto 0);
            d   : in    unsigned(31 downto 0);
    
            a2  : out   unsigned(31 downto 0);
            b2  : out   unsigned(31 downto 0);
            c2  : out   unsigned(31 downto 0);
            d2  : out   unsigned(31 downto 0);
    
            done: out   unsigned(0 downto 0)
        );
    end component;

signal clk_9600     : std_ulogic            := '0';
signal uart_txbyte  : unsigned(7 downto 0)  := to_unsigned(0, 8);
signal uart_send    : unsigned(0 downto 0)  := "0";
signal uart_txed    : unsigned(0 downto 0)  := "0";
signal uart_tx      : unsigned(0 downto 0)  := "0";
signal cntr_9600    : unsigned(31 downto 0) := (others => '0');
signal period9600   : unsigned(31 downto 0) := to_unsigned(625, 32);

signal cntr_32    : unsigned(31 downto 0) := (others => '0');
signal txidleSignal : unsigned(0 downto 0);


signal a    : unsigned(31 downto 0) := to_unsigned(0, 32);
signal b    : unsigned(31 downto 0) := to_unsigned(0, 32);
signal c    : unsigned(31 downto 0) := to_unsigned(0, 32);
signal d    : unsigned(31 downto 0) := to_unsigned(0, 32);
signal a2   : unsigned(31 downto 0);
signal b2   : unsigned(31 downto 0);
signal c2   : unsigned(31 downto 0);
signal d2   : unsigned(31 downto 0);

signal done : unsigned(0 downto 0);
signal txDoneSignal : unsigned(0 downto 0);
--signal a3 : unsigned(31 downto 0) := "10101010101110111100110011011101";

signal hwclk : std_logic := '0';

begin
    hwclk <= not hwclk after 10 ns;

    uartInstance: uart8n1_tx 
    port map
    (
        clk => clk_9600,
        en => "1",
        txByte => uart_txbyte,
        sendData => "1",
        isIdle => txidleSignal,
        txDone => txDoneSignal,
        tx => ftdi_tx
    );

    chacha_qrInstance: chacha_qr
    port map
    (
        clk => hwclk,
        a => to_unsigned(1, 32),
        b => b,
        c => c,
        d => d,

        a2 => a2,
        b2 => b2,
        c2 => c2,
        d2 => d2,
        done => done
    );

    process (hwclk)
        variable state: unsigned(2 downto 0) := "000";
        variable counter: integer := 0;
    begin
        if rising_edge(hwclk) then
            ledGreen <= "0";
            cntr_9600 <= cntr_9600 + 1;
            cntr_32 <= cntr_32 + 1;

            if (cntr_9600 = period9600) then
                clk_9600 <= not clk_9600;
                cntr_9600 <= to_unsigned(0, 32);
            end if;

            --uart_txbyte <= to_unsigned(50, 8);
            if (txidleSignal = "1" and done = "1") then
                uart_txbyte <= "00110011";
            end if;

            if ((txDoneSignal = "1" or txidleSignal = "1") and done = "1") then
                uart_txbyte <= to_unsigned(138, 8);
                if (state = "000") then
                    led0 <= "0";
                    uart_txbyte <= a2(7 downto 0) xor b2(7 downto 0) xor c2(7 downto 0) xor d2(7 downto 0);
                    state := state + 1;
                    report "The value of 'uart_txbyte' is " & integer'image(to_integer(uart_txbyte));

                elsif (state = "001") then
                    uart_txbyte <= a2(15 downto 8) xor b2(15 downto 8) xor c2(15 downto 8) xor d2(15 downto 8);
                    state := state + 1;
                    report "The value of 'uart_txbyte' is " & integer'image(to_integer(uart_txbyte));

                elsif (state = "010") then
                    uart_txbyte <= a2(23 downto 16) xor b2(23 downto 16) xor c2(23 downto 16) xor d2(23 downto 16);
                    state := state + 1;
                    report "The value of 'uart_txbyte' is " & integer'image(to_integer(uart_txbyte));

                elsif (state = "011") then
                    uart_txbyte <= a2(31 downto 24) xor b2(31 downto 24) xor c2(31 downto 24) xor d2(31 downto 24);
                    state := "000";
                    report "The value of 'uart_txbyte' is " & integer'image(to_integer(uart_txbyte));
                    report "end" severity failure;
                end if;
            end if;
        end if;
    end process;

end test;

6/VHDL/uartTxTest/txTest/sim.vcd
$date
  Sun May  8 18:31:32 2022
$end
$version
  GHDL v0
$end
$timescale
  1 fs
$end
$scope module standard $end
$upscope $end
$scope module std_logic_1164 $end
$upscope $end
$scope module numeric_std $end
$upscope $end
$scope module uart8n1_tx2_tb $end
$var reg 1 ! ledgreen[0:0] $end
$var reg 1 " led0[0:0] $end
$var reg 1 # ftdi_tx[0:0] $end
$var reg 1 $ clk_9600 $end
$var reg 8 % uart_txbyte[7:0] $end
$var reg 1 & uart_send[0:0] $end
$var reg 1 ' uart_txed[0:0] $end
$var reg 1 ( uart_tx[0:0] $end
$var reg 32 ) cntr_9600[31:0] $end
$var reg 32 * period9600[31:0] $end
$var reg 32 + cntr_32[31:0] $end
$var reg 1 , txidlesignal[0:0] $end
$var reg 32 - a[31:0] $end
$var reg 32 . b[31:0] $end
$var reg 32 / c[31:0] $end
$var reg 32 0 d[31:0] $end
$var reg 32 1 a2[31:0] $end
$var reg 32 2 b2[31:0] $end
$var reg 32 3 c2[31:0] $end
$var reg 32 4 d2[31:0] $end
$var reg 1 5 done[0:0] $end
$var reg 1 6 txdonesignal[0:0] $end
$var reg 1 7 hwclk $end
$scope module uartinstance $end
$var reg 1 8 clk $end
$var reg 1 9 en[0:0] $end
$var reg 8 : txbyte[7:0] $end
$var reg 1 ; senddata[0:0] $end
$var reg 1 < isidle[0:0] $end
$var reg 1 = txdone[0:0] $end
$var reg 1 > tx[0:0] $end
$var reg 1 ? txbit[0:0] $end
$var reg 1 @ isidlesignal[0:0] $end
$var reg 1 A isdonesignal[0:0] $end
$upscope $end
$scope module chacha_qrinstance $end
$var reg 1 B clk $end
$var reg 32 C a[31:0] $end
$var reg 32 D b[31:0] $end
$var reg 32 E c[31:0] $end
$var reg 32 F d[31:0] $end
$var reg 32 G a2[31:0] $end
$var reg 32 H b2[31:0] $end
$var reg 32 I c2[31:0] $end
$var reg 32 J d2[31:0] $end
$var reg 1 K done[0:0] $end
$var reg 32 L a2signal[31:0] $end
$var reg 32 M b2signal[31:0] $end
$var reg 32 N c2signal[31:0] $end
$var reg 32 O d2signal[31:0] $end
$upscope $end
$upscope $end
$enddefinitions $end
#0
bU !
bU "
b1 #
0$
b00000000 %
b0 &
b0 '
b0 (
b00000000000000000000000000000000 )
b00000000000000000000001001110001 *
b00000000000000000000000000000000 +
b1 ,
b00000000000000000000000000000000 -
b00000000000000000000000000000000 .
b00000000000000000000000000000000 /
b00000000000000000000000000000000 0
bUUUUUUUUUUUUUUUUUUUUUUUUUUUUUUUU 1
bUUUUUUUUUUUUUUUUUUUUUUUUUUUUUUUU 2
bUUUUUUUUUUUUUUUUUUUUUUUUUUUUUUUU 3
bUUUUUUUUUUUUUUUUUUUUUUUUUUUUUUUU 4
bU 5
b1 6
07
08
b1 9
b00000000 :
b1 ;
b1 <
b1 =
b1 >
b1 ?
b1 @
b1 A
0B
b00000000000000000000000000000001 C
b00000000000000000000000000000000 D
b00000000000000000000000000000000 E
b00000000000000000000000000000000 F
bUUUUUUUUUUUUUUUUUUUUUUUUUUUUUUUU G
bUUUUUUUUUUUUUUUUUUUUUUUUUUUUUUUU H
bUUUUUUUUUUUUUUUUUUUUUUUUUUUUUUUU I
bUUUUUUUUUUUUUUUUUUUUUUUUUUUUUUUU J
bU K
bUUUUUUUUUUUUUUUUUUUUUUUUUUUUUUUU L
bUUUUUUUUUUUUUUUUUUUUUUUUUUUUUUUU M
bUUUUUUUUUUUUUUUUUUUUUUUUUUUUUUUU N
bUUUUUUUUUUUUUUUUUUUUUUUUUUUUUUUU O
#10000000
b0 !
b00000000000000000000000000000001 )
b00000000000000000000000000000001 +
b00000000000000000000000000000001 1
b00000000000000000000000000000000 2
b00000000000000000000000000000000 3
bUUUUUUUUUUUUUUUU0000000000000000 4
b0 5
17
1B
b00000000000000000000000000000001 G
b00000000000000000000000000000000 H
b00000000000000000000000000000000 I
bUUUUUUUUUUUUUUUU0000000000000000 J
b0 K
b00000000000000000000000000000001 L
b00000000000000000000000000000000 M
b00000000000000000000000000000000 N
bUUUUUUUUUUUUUUUU0000000000000000 O
#20000000
07
0B
#30000000
b00000000000000000000000000000010 )
b00000000000000000000000000000010 +
bXXXXXXXXXXXXXXXXXXXXXXXXXXXXXXXX 3
17
1B
bXXXXXXXXXXXXXXXXXXXXXXXXXXXXXXXX I
bXXXXXXXXXXXXXXXXXXXXXXXXXXXXXXXX N
#40000000
07
0B
#50000000
b00000000000000000000000000000011 )
b00000000000000000000000000000011 +
bUUUUUUUU000000000000000100000000 4
17
1B
bUUUUUUUU000000000000000100000000 J
bUUUUUUUU000000000000000100000000 O
#60000000
07
0B
#70000000
b00000000000000000000000000000100 )
b00000000000000000000000000000100 +
bXXXXXXXXXXXXXXXXXXXXXXXXX0000000 2
17
1B
bXXXXXXXXXXXXXXXXXXXXXXXXX0000000 H
bXXXXXXXXXXXXXXXXXXXXXXXXX0000000 M
#80000000
07
0B
#90000000
b00000000000000000000000000000101 )
b00000000000000000000000000000101 +
b00000000000000000000000000000000 2
b00000000000000000000000000000000 3
b00000000000000010000000000000000 4
17
1B
b00000000000000000000000000000000 H
b00000000000000000000000000000000 I
b00000000000000010000000000000000 J
b00000000000000000000000000000000 M
b00000000000000000000000000000000 N
b00000000000000010000000000000000 O
#100000000
07
0B
#110000000
b00000000000000000000000000000110 )
b00000000000000000000000000000110 +
b00000000000000010000000000000000 3
17
1B
b00000000000000010000000000000000 I
b00000000000000010000000000000000 N
#120000000
07
0B
#130000000
b00000000000000000000000000000111 )
b00000000000000000000000000000111 +
b00000001000000000000000100000000 4
17
1B
b00000001000000000000000100000000 J
b00000001000000000000000100000000 O
#140000000
07
0B
#150000000
b00000000000000000000000000001000 )
b00000000000000000000000000001000 +
b00000000100000000000000000000000 2
b00000001000000010000000100000000 3
17
1B
b00000000100000000000000000000000 H
b00000001000000010000000100000000 I
b00000000100000000000000000000000 M
b00000001000000010000000100000000 N
#160000000
07
0B
#170000000
b00000000000000000000000000001001 )
b00000000000000000000000000001001 +
b00000000000000000000000000000000 2
b00000000000000000000000000000000 3
b00000000000000010000000000000000 4
17
1B
b00000000000000000000000000000000 H
b00000000000000000000000000000000 I
b00000000000000010000000000000000 J
b00000000000000000000000000000000 M
b00000000000000000000000000000000 N
b00000000000000010000000000000000 O
#180000000
07
0B
#190000000
b00000000000000000000000000001010 )
b00000000000000000000000000001010 +
b00000000000000010000000000000000 3
17
1B
b00000000000000010000000000000000 I
b00000000000000010000000000000000 N
#200000000
07
0B
#210000000
b00000000000000000000000000001011 )
b00000000000000000000000000001011 +
b00000001000000000000000100000000 4
17
1B
b00000001000000000000000100000000 J
b00000001000000000000000100000000 O
#220000000
07
0B
#230000000
b00000000000000000000000000001100 )
b00000000000000000000000000001100 +
b00000000100000000000000000000000 2
b00000001000000010000000100000000 3
17
1B
b00000000100000000000000000000000 H
b00000001000000010000000100000000 I
b00000000100000000000000000000000 M
b00000001000000010000000100000000 N
#240000000
07
0B
#250000000
b00000000000000000000000000001101 )
b00000000000000000000000000001101 +
b00000000000000000000000000000000 2
b00000000000000000000000000000000 3
b00000000000000010000000000000000 4
17
1B
b00000000000000000000000000000000 H
b00000000000000000000000000000000 I
b00000000000000010000000000000000 J
b00000000000000000000000000000000 M
b00000000000000000000000000000000 N
b00000000000000010000000000000000 O
#260000000
07
0B
#270000000
b00000000000000000000000000001110 )
b00000000000000000000000000001110 +
b00000000000000010000000000000000 3
17
1B
b00000000000000010000000000000000 I
b00000000000000010000000000000000 N
#280000000
07
0B
#290000000
b00000000000000000000000000001111 )
b00000000000000000000000000001111 +
b00000001000000000000000100000000 4
17
1B
b00000001000000000000000100000000 J
b00000001000000000000000100000000 O
#300000000
07
0B
#310000000
b00000000000000000000000000010000 )
b00000000000000000000000000010000 +
b00000000100000000000000000000000 2
b00000001000000010000000100000000 3
17
1B
b00000000100000000000000000000000 H
b00000001000000010000000100000000 I
b00000000100000000000000000000000 M
b00000001000000010000000100000000 N
#320000000
07
0B
#330000000
b00000000000000000000000000010001 )
b00000000000000000000000000010001 +
b00000000000000000000000000000000 2
b00000000000000000000000000000000 3
b00000000000000010000000000000000 4
17
1B
b00000000000000000000000000000000 H
b00000000000000000000000000000000 I
b00000000000000010000000000000000 J
b00000000000000000000000000000000 M
b00000000000000000000000000000000 N
b00000000000000010000000000000000 O
#340000000
07
0B
#350000000
b00000000000000000000000000010010 )
b00000000000000000000000000010010 +
b00000000000000010000000000000000 3
17
1B
b00000000000000010000000000000000 I
b00000000000000010000000000000000 N
#360000000
07
0B
#370000000
b00000000000000000000000000010011 )
b00000000000000000000000000010011 +
b00000001000000000000000100000000 4
17
1B
b00000001000000000000000100000000 J
b00000001000000000000000100000000 O
#380000000
07
0B
#390000000
b00000000000000000000000000010100 )
b00000000000000000000000000010100 +
b00000000100000000000000000000000 2
b00000001000000010000000100000000 3
17
1B
b00000000100000000000000000000000 H
b00000001000000010000000100000000 I
b00000000100000000000000000000000 M
b00000001000000010000000100000000 N
#400000000
07
0B
#410000000
b00000000000000000000000000010101 )
b00000000000000000000000000010101 +
b00000000000000000000000000000000 2
b00000000000000000000000000000000 3
b00000000000000010000000000000000 4
17
1B
b00000000000000000000000000000000 H
b00000000000000000000000000000000 I
b00000000000000010000000000000000 J
b00000000000000000000000000000000 M
b00000000000000000000000000000000 N
b00000000000000010000000000000000 O
#420000000
07
0B
#430000000
b00000000000000000000000000010110 )
b00000000000000000000000000010110 +
b00000000000000010000000000000000 3
17
1B
b00000000000000010000000000000000 I
b00000000000000010000000000000000 N
#440000000
07
0B
#450000000
b00000000000000000000000000010111 )
b00000000000000000000000000010111 +
b00000001000000000000000100000000 4
17
1B
b00000001000000000000000100000000 J
b00000001000000000000000100000000 O
#460000000
07
0B
#470000000
b00000000000000000000000000011000 )
b00000000000000000000000000011000 +
b00000000100000000000000000000000 2
b00000001000000010000000100000000 3
17
1B
b00000000100000000000000000000000 H
b00000001000000010000000100000000 I
b00000000100000000000000000000000 M
b00000001000000010000000100000000 N
#480000000
07
0B
#490000000
b00000000000000000000000000011001 )
b00000000000000000000000000011001 +
b00000000000000000000000000000000 2
b00000000000000000000000000000000 3
b00000000000000010000000000000000 4
17
1B
b00000000000000000000000000000000 H
b00000000000000000000000000000000 I
b00000000000000010000000000000000 J
b00000000000000000000000000000000 M
b00000000000000000000000000000000 N
b00000000000000010000000000000000 O
#500000000
07
0B
#510000000
b00000000000000000000000000011010 )
b00000000000000000000000000011010 +
b00000000000000010000000000000000 3
17
1B
b00000000000000010000000000000000 I
b00000000000000010000000000000000 N
#520000000
07
0B
#530000000
b00000000000000000000000000011011 )
b00000000000000000000000000011011 +
b00000001000000000000000100000000 4
17
1B
b00000001000000000000000100000000 J
b00000001000000000000000100000000 O
#540000000
07
0B
#550000000
b00000000000000000000000000011100 )
b00000000000000000000000000011100 +
b00000000100000000000000000000000 2
b00000001000000010000000100000000 3
17
1B
b00000000100000000000000000000000 H
b00000001000000010000000100000000 I
b00000000100000000000000000000000 M
b00000001000000010000000100000000 N
#560000000
07
0B
#570000000
b00000000000000000000000000011101 )
b00000000000000000000000000011101 +
b00000000000000000000000000000000 2
b00000000000000000000000000000000 3
b00000000000000010000000000000000 4
17
1B
b00000000000000000000000000000000 H
b00000000000000000000000000000000 I
b00000000000000010000000000000000 J
b00000000000000000000000000000000 M
b00000000000000000000000000000000 N
b00000000000000010000000000000000 O
#580000000
07
0B
#590000000
b00000000000000000000000000011110 )
b00000000000000000000000000011110 +
b00000000000000010000000000000000 3
17
1B
b00000000000000010000000000000000 I
b00000000000000010000000000000000 N
#600000000
07
0B
#610000000
b00000000000000000000000000011111 )
b00000000000000000000000000011111 +
b00000001000000000000000100000000 4
17
1B
b00000001000000000000000100000000 J
b00000001000000000000000100000000 O
#620000000
07
0B
#630000000
b00000000000000000000000000100000 )
b00000000000000000000000000100000 +
b00000000100000000000000000000000 2
b00000001000000010000000100000000 3
17
1B
b00000000100000000000000000000000 H
b00000001000000010000000100000000 I
b00000000100000000000000000000000 M
b00000001000000010000000100000000 N
#640000000
07
0B
#650000000
b00000000000000000000000000100001 )
b00000000000000000000000000100001 +
b00000000000000000000000000000000 2
b00000000000000000000000000000000 3
b00000000000000010000000000000000 4
17
1B
b00000000000000000000000000000000 H
b00000000000000000000000000000000 I
b00000000000000010000000000000000 J
b00000000000000000000000000000000 M
b00000000000000000000000000000000 N
b00000000000000010000000000000000 O
#660000000
07
0B
#670000000
b00000000000000000000000000100010 )
b00000000000000000000000000100010 +
b00000000000000010000000000000000 3
17
1B
b00000000000000010000000000000000 I
b00000000000000010000000000000000 N
#680000000
07
0B
#690000000
b00000000000000000000000000100011 )
b00000000000000000000000000100011 +
b00000001000000000000000100000000 4
17
1B
b00000001000000000000000100000000 J
b00000001000000000000000100000000 O
#700000000
07
0B
#710000000
b00000000000000000000000000100100 )
b00000000000000000000000000100100 +
b00000000100000000000000000000000 2
b00000001000000010000000100000000 3
17
1B
b00000000100000000000000000000000 H
b00000001000000010000000100000000 I
b00000000100000000000000000000000 M
b00000001000000010000000100000000 N
#720000000
07
0B
#730000000
b00000000000000000000000000100101 )
b00000000000000000000000000100101 +
b00000000000000000000000000000000 2
b00000000000000000000000000000000 3
b00000000000000010000000000000000 4
17
1B
b00000000000000000000000000000000 H
b00000000000000000000000000000000 I
b00000000000000010000000000000000 J
b00000000000000000000000000000000 M
b00000000000000000000000000000000 N
b00000000000000010000000000000000 O
#740000000
07
0B
#750000000
b00000000000000000000000000100110 )
b00000000000000000000000000100110 +
b00000000000000010000000000000000 3
17
1B
b00000000000000010000000000000000 I
b00000000000000010000000000000000 N
#760000000
07
0B
#770000000
b00000000000000000000000000100111 )
b00000000000000000000000000100111 +
b00000001000000000000000100000000 4
17
1B
b00000001000000000000000100000000 J
b00000001000000000000000100000000 O
#780000000
07
0B
#790000000
b00000000000000000000000000101000 )
b00000000000000000000000000101000 +
b00000000100000000000000000000000 2
b00000001000000010000000100000000 3
17
1B
b00000000100000000000000000000000 H
b00000001000000010000000100000000 I
b00000000100000000000000000000000 M
b00000001000000010000000100000000 N
#800000000
07
0B
#810000000
b00000000000000000000000000101001 )
b00000000000000000000000000101001 +
b00000000000000000000000000000000 2
b00000000000000000000000000000000 3
b00000000000000010000000000000000 4
17
1B
b00000000000000000000000000000000 H
b00000000000000000000000000000000 I
b00000000000000010000000000000000 J
b00000000000000000000000000000000 M
b00000000000000000000000000000000 N
b00000000000000010000000000000000 O
#820000000
07
0B
#830000000
b00000000000000000000000000101010 )
b00000000000000000000000000101010 +
b00000000000000010000000000000000 3
17
1B
b00000000000000010000000000000000 I
b00000000000000010000000000000000 N
#840000000
07
0B
#850000000
b00000000000000000000000000101011 )
b00000000000000000000000000101011 +
b00000001000000000000000100000000 4
17
1B
b00000001000000000000000100000000 J
b00000001000000000000000100000000 O
#860000000
07
0B
#870000000
b00000000000000000000000000101100 )
b00000000000000000000000000101100 +
b00000000100000000000000000000000 2
b00000001000000010000000100000000 3
17
1B
b00000000100000000000000000000000 H
b00000001000000010000000100000000 I
b00000000100000000000000000000000 M
b00000001000000010000000100000000 N
#880000000
07
0B
#890000000
b00000000000000000000000000101101 )
b00000000000000000000000000101101 +
b00000000000000000000000000000000 2
b00000000000000000000000000000000 3
b00000000000000010000000000000000 4
17
1B
b00000000000000000000000000000000 H
b00000000000000000000000000000000 I
b00000000000000010000000000000000 J
b00000000000000000000000000000000 M
b00000000000000000000000000000000 N
b00000000000000010000000000000000 O
#900000000
07
0B
#910000000
b00000000000000000000000000101110 )
b00000000000000000000000000101110 +
b00000000000000010000000000000000 3
17
1B
b00000000000000010000000000000000 I
b00000000000000010000000000000000 N
#920000000
07
0B
#930000000
b00000000000000000000000000101111 )
b00000000000000000000000000101111 +
b00000001000000000000000100000000 4
17
1B
b00000001000000000000000100000000 J
b00000001000000000000000100000000 O
#940000000
07
0B
#950000000
b00000000000000000000000000110000 )
b00000000000000000000000000110000 +
b00000000100000000000000000000000 2
b00000001000000010000000100000000 3
17
1B
b00000000100000000000000000000000 H
b00000001000000010000000100000000 I
b00000000100000000000000000000000 M
b00000001000000010000000100000000 N
#960000000
07
0B
#970000000
b00000000000000000000000000110001 )
b00000000000000000000000000110001 +
b00000000000000000000000000000000 2
b00000000000000000000000000000000 3
b00000000000000010000000000000000 4
17
1B
b00000000000000000000000000000000 H
b00000000000000000000000000000000 I
b00000000000000010000000000000000 J
b00000000000000000000000000000000 M
b00000000000000000000000000000000 N
b00000000000000010000000000000000 O
#980000000
07
0B
#990000000
b00000000000000000000000000110010 )
b00000000000000000000000000110010 +
b00000000000000010000000000000000 3
17
1B
b00000000000000010000000000000000 I
b00000000000000010000000000000000 N
#1000000000
07
0B
#1010000000
b00000000000000000000000000110011 )
b00000000000000000000000000110011 +
b00000001000000000000000100000000 4
17
1B
b00000001000000000000000100000000 J
b00000001000000000000000100000000 O
#1020000000
07
0B
#1030000000
b00000000000000000000000000110100 )
b00000000000000000000000000110100 +
b00000000100000000000000000000000 2
b00000001000000010000000100000000 3
17
1B
b00000000100000000000000000000000 H
b00000001000000010000000100000000 I
b00000000100000000000000000000000 M
b00000001000000010000000100000000 N
#1040000000
07
0B
#1050000000
b00000000000000000000000000110101 )
b00000000000000000000000000110101 +
b00000000000000000000000000000000 2
b00000000000000000000000000000000 3
b00000000000000010000000000000000 4
17
1B
b00000000000000000000000000000000 H
b00000000000000000000000000000000 I
b00000000000000010000000000000000 J
b00000000000000000000000000000000 M
b00000000000000000000000000000000 N
b00000000000000010000000000000000 O
#1060000000
07
0B
#1070000000
b00000000000000000000000000110110 )
b00000000000000000000000000110110 +
b00000000000000010000000000000000 3
17
1B
b00000000000000010000000000000000 I
b00000000000000010000000000000000 N
#1080000000
07
0B
#1090000000
b00000000000000000000000000110111 )
b00000000000000000000000000110111 +
b00000001000000000000000100000000 4
17
1B
b00000001000000000000000100000000 J
b00000001000000000000000100000000 O
#1100000000
07
0B
#1110000000
b00000000000000000000000000111000 )
b00000000000000000000000000111000 +
b00000000100000000000000000000000 2
b00000001000000010000000100000000 3
17
1B
b00000000100000000000000000000000 H
b00000001000000010000000100000000 I
b00000000100000000000000000000000 M
b00000001000000010000000100000000 N
#1120000000
07
0B
#1130000000
b00000000000000000000000000111001 )
b00000000000000000000000000111001 +
b00000000000000000000000000000000 2
b00000000000000000000000000000000 3
b00000000000000010000000000000000 4
17
1B
b00000000000000000000000000000000 H
b00000000000000000000000000000000 I
b00000000000000010000000000000000 J
b00000000000000000000000000000000 M
b00000000000000000000000000000000 N
b00000000000000010000000000000000 O
#1140000000
07
0B
#1150000000
b00000000000000000000000000111010 )
b00000000000000000000000000111010 +
b00000000000000010000000000000000 3
17
1B
b00000000000000010000000000000000 I
b00000000000000010000000000000000 N
#1160000000
07
0B
#1170000000
b00000000000000000000000000111011 )
b00000000000000000000000000111011 +
b00000001000000000000000100000000 4
17
1B
b00000001000000000000000100000000 J
b00000001000000000000000100000000 O
#1180000000
07
0B
#1190000000
b00000000000000000000000000111100 )
b00000000000000000000000000111100 +
b00000000100000000000000000000000 2
b00000001000000010000000100000000 3
17
1B
b00000000100000000000000000000000 H
b00000001000000010000000100000000 I
b00000000100000000000000000000000 M
b00000001000000010000000100000000 N
#1200000000
07
0B
#1210000000
b00000000000000000000000000111101 )
b00000000000000000000000000111101 +
b00000000000000000000000000000000 2
b00000000000000000000000000000000 3
b00000000000000010000000000000000 4
17
1B
b00000000000000000000000000000000 H
b00000000000000000000000000000000 I
b00000000000000010000000000000000 J
b00000000000000000000000000000000 M
b00000000000000000000000000000000 N
b00000000000000010000000000000000 O
#1220000000
07
0B
#1230000000
b00000000000000000000000000111110 )
b00000000000000000000000000111110 +
b00000000000000010000000000000000 3
17
1B
b00000000000000010000000000000000 I
b00000000000000010000000000000000 N
#1240000000
07
0B
#1250000000
b00000000000000000000000000111111 )
b00000000000000000000000000111111 +
b00000001000000000000000100000000 4
17
1B
b00000001000000000000000100000000 J
b00000001000000000000000100000000 O
#1260000000
07
0B
#1270000000
b00000000000000000000000001000000 )
b00000000000000000000000001000000 +
b00000000100000000000000000000000 2
b00000001000000010000000100000000 3
17
1B
b00000000100000000000000000000000 H
b00000001000000010000000100000000 I
b00000000100000000000000000000000 M
b00000001000000010000000100000000 N
#1280000000
07
0B
#1290000000
b00000000000000000000000001000001 )
b00000000000000000000000001000001 +
b00000000000000000000000000000000 2
b00000000000000000000000000000000 3
b00000000000000010000000000000000 4
17
1B
b00000000000000000000000000000000 H
b00000000000000000000000000000000 I
b00000000000000010000000000000000 J
b00000000000000000000000000000000 M
b00000000000000000000000000000000 N
b00000000000000010000000000000000 O
#1300000000
07
0B
#1310000000
b00000000000000000000000001000010 )
b00000000000000000000000001000010 +
b00000000000000010000000000000000 3
17
1B
b00000000000000010000000000000000 I
b00000000000000010000000000000000 N
#1320000000
07
0B
#1330000000
b00000000000000000000000001000011 )
b00000000000000000000000001000011 +
b00000001000000000000000100000000 4
17
1B
b00000001000000000000000100000000 J
b00000001000000000000000100000000 O
#1340000000
07
0B
