6/VHDL/uartTxTest/txTest/chacha_qr.vhdl
library ieee;
use ieee.std_logic_1164.all;
use ieee.numeric_std.all;

entity chacha_qr is
    port 
    (
        clk : in    std_ulogic;

        a   : in    unsigned(31 downto 0);
        b   : in    unsigned(31 downto 0);
        c   : in    unsigned(31 downto 0);
        d   : in    unsigned(31 downto 0);

        a2  : out   unsigned(31 downto 0);
        b2  : out   unsigned(31 downto 0);
        c2  : out   unsigned(31 downto 0);
        d2  : out   unsigned(31 downto 0);

        done: out   unsigned(0 downto 0)
    );
end chacha_qr;

architecture behave of chacha_qr is
signal a0Signal: unsigned(31 downto 0);
signal b0Signal: unsigned(31 downto 0);
signal c0Signal: unsigned(31 downto 0);
signal d0Signal: unsigned(31 downto 0);

signal a1Signal: unsigned(31 downto 0);
signal b1Signal: unsigned(31 downto 0);
signal c1Signal: unsigned(31 downto 0);
signal d1Signal: unsigned(31 downto 0);

signal a2Signal: unsigned(31 downto 0);
signal b2Signal: unsigned(31 downto 0);
signal c2Signal: unsigned(31 downto 0);
signal d2Signal: unsigned(31 downto 0);

signal a3Signal: unsigned(31 downto 0);
signal b3Signal: unsigned(31 downto 0);
signal c3Signal: unsigned(31 downto 0);
signal d3Signal: unsigned(31 downto 0);

signal aSignal: unsigned(31 downto 0);
signal bSignal: unsigned(31 downto 0);
signal cSignal: unsigned(31 downto 0);
signal dSignal: unsigned(31 downto 0);

begin
    a2 <= aSignal;
    b2 <= bSignal;
    c2 <= cSignal;
    d2 <= dSignal;

    process (clk)
        variable state:     unsigned(1 downto 0) := "00";
        variable index:     unsigned(4 downto 0) := "00000";
        constant maxIndex:  unsigned(4 downto 0) := to_unsigned(20, 5);
    begin
        if (rising_edge(clk)) then
            if (state = "00") then
                if (index = "00000") then
                    a0Signal <= a + b;
                    b0Signal <= b;
                    c0Signal <= c;
                    d0Signal <= (d xor (a + b)) sll 16;

                else 
                    a0Signal <= aSignal + bSignal;
                    b0Signal <= bSignal;
                    c0Signal <= cSignal;
                    d0Signal <= (dSignal xor (aSignal + bSignal)) sll 16;
                end if;
                done <= "0";
                state := "01";

            elsif (state = "01") then
                --c += d; b ^= c; b <<<= 12;
                a1Signal <= a0Signal;
                d1Signal <= d0Signal;
                c1Signal <= c0Signal + d0Signal;
                b1Signal <= (b0Signal xor (c0Signal + d0Signal)) sll 12;
                state := "10";

            elsif (state = "10") then
                --a += b; d ^= a; d <<<= 8;
                b2Signal <= b1Signal;
                c2Signal <= c1Signal;
                a2Signal <= a1Signal + b1Signal;
                d2Signal <= (d1Signal xor (a1Signal + b1Signal)) sll 8;
                state := "11";

            else
                --c += d; b ^= c; b <<<= 7;
                a3Signal <= a2Signal;
                d3Signal <= d2Signal;
                c3Signal <= c2Signal + d2Signal;
                b3Signal <= (b2Signal xor (c2Signal + d2Signal)) sll 7;

                aSignal <= a3Signal;
                dSignal <= d3Signal;
                cSignal <= c3Signal;
                bSignal <= b3Signal;

                done <= "1";
                if (index = maxIndex and state = "11") then
                    done <= "1";
                    index := "00000";
                
                else
                    index := index + 1;
                end if;

                state := "00";
            end if;
        end if;
    end process;
end behave;

6/VHDL/uartTxTest/txTest/uart8n1_tx.vhdl
library ieee;
use ieee.std_logic_1164.all;
use ieee.numeric_std.all;

entity uart8n1_tx is
    port 
    (
        clk     : in    std_ulogic;
        en      : in    unsigned(0 downto 0);
        txByte  : in    unsigned(7 downto 0);
        sendData: in    unsigned(0 downto 0);

        isIdle  : out   unsigned(0 downto 0);
        txDone  : out   unsigned(0 downto 0);
        tx      : out   unsigned(0 downto 0)
    );

subtype st_logicBit is std_ulogic;
subtype st_bit is unsigned(0 downto 0);
subtype st_byte is unsigned(7 downto 0);
subtype state_t is unsigned(1 downto 0);
end uart8n1_tx;

architecture behave of uart8n1_tx is
signal txBit: st_bit    := "1";
--signal bufTx: st_byte   := "00000000";

signal isidleSignal: unsigned(0 downto 0) := "1";
signal isDoneSignal: unsigned(0 downto 0) := "1";

begin
    tx <= txBit;
    isIdle <= isidleSignal;
    txDone <= isDoneSignal;

    --bufTx <= txByte;

    process (clk)
    
    constant StateIdle      : state_t   := "00";
    constant StateStartTx   : state_t   := "01";
    constant StateTxing     : state_t   := "10";
    constant StateTxDone    : state_t   := "11";

    variable state          : state_t   := StateIdle;
    variable bufTx: st_byte   := "00000000";
    variable bitsSent       : st_byte   := "00000000";
    --variable txBit          : _bit    := "1";*/

    begin
        if (rising_edge(clk) and en = "1") then
            if (state = StateIdle) then
                isidleSignal <= "1";
                if (sendData = "1" and state = StateIdle) then
                    state := StateStartTx;
                    bufTx := txByte;
                    isDoneSignal <= "0";

                elsif (state = StateIdle) then
                    txBit <= "1";
                    isDoneSignal <= "0";
                end if;

            elsif (state = StateStartTx) then
                isidleSignal <= "0";
                if (state = StateStartTx) then
                    txBit <= "0";
                    state := StateTxing;
                end if;

            elsif (state = StateTxing) then
                isidleSignal <= "0";
                if (state = StateTxing and bitsSent < to_unsigned(8, 8)) then
                    txBit <= bufTx(0 downto 0);
                    bufTx := shift_right(bufTx, 1);
                    bitsSent := bitsSent + 1;
            
                elsif (state = StateTxing) then
                    txBit <= "1";
                    bitsSent := "00000000";
                    state := StateTxDone;
                end if;

            elsif (state = StateTxDone) then
                isidleSignal <= "0";
                if (state = StateTxDone) then
                    isDoneSignal <= "1";
                    state := StateIdle;
                end if;
            end if;
        end if;

    end process;
end behave;

6/VHDL/uartTxTest/txTest/uart8n1_tx2_tb.vhdl
library ieee;
use ieee.std_logic_1164.all;
use ieee.numeric_std.all;

entity uart8n1_tx2_tb is
    port 
    (
        --hwclk     : in      std_ulogic;
        ledGreen  : out     unsigned(0 downto 0);
        led0      : out     unsigned(0 downto 0);
        ftdi_tx   : out     unsigned(0 downto 0)
    );
end uart8n1_tx2_tb;

architecture test of uart8n1_tx2_tb is
    component uart8n1_tx
        port 
        (
            clk     : in    std_ulogic;
            en      : in    unsigned(0 downto 0);
            txByte  : in    unsigned(7 downto 0);
            sendData: in    unsigned(0 downto 0);
    
            isIdle  : out   unsigned(0 downto 0);
            txDone  : out   unsigned(0 downto 0);
            tx      : out   unsigned(0 downto 0)
        );
    end component;

    component chacha_qr
        port 
        (
            clk : in    std_ulogic;
    
            a   : in    unsigned(31 downto 0);
            b   : in    unsigned(31 downto 0);
            c   : in    unsigned(31 downto 0);
            d   : in    unsigned(31 downto 0);
    
            a2  : out   unsigned(31 downto 0);
            b2  : out   unsigned(31 downto 0);
            c2  : out   unsigned(31 downto 0);
            d2  : out   unsigned(31 downto 0);
    
            done: out   unsigned(0 downto 0)
        );
    end component;

signal clk_9600     : std_ulogic            := '0';
signal uart_txbyte  : unsigned(7 downto 0)  := to_unsigned(0, 8);
signal uart_send    : unsigned(0 downto 0)  := "0";
signal uart_txed    : unsigned(0 downto 0)  := "0";
signal uart_tx      : unsigned(0 downto 0)  := "0";
signal cntr_9600    : unsigned(31 downto 0) := (others => '0');
signal period9600   : unsigned(31 downto 0) := to_unsigned(625, 32);

signal cntr_32    : unsigned(31 downto 0) := (others => '0');
signal txidleSignal : unsigned(0 downto 0);


signal a    : unsigned(31 downto 0) := to_unsigned(0, 32);
signal b    : unsigned(31 downto 0) := to_unsigned(0, 32);
signal c    : unsigned(31 downto 0) := to_unsigned(0, 32);
signal d    : unsigned(31 downto 0) := to_unsigned(0, 32);
signal a2   : unsigned(31 downto 0);
signal b2   : unsigned(31 downto 0);
signal c2   : unsigned(31 downto 0);
signal d2   : unsigned(31 downto 0);

signal done : unsigned(0 downto 0);
signal txDoneSignal : unsigned(0 downto 0);
--signal a3 : unsigned(31 downto 0) := "10101010101110111100110011011101";

signal hwclk : std_logic := '0';

begin
    hwclk <= not hwclk after 10 ns;

    uartInstance: uart8n1_tx 
    port map
    (
        clk => clk_9600,
        en => "1",
        txByte => uart_txbyte,
        sendData => "1",
        isIdle => txidleSignal,
        txDone => txDoneSignal,
        tx => ftdi_tx
    );

    chacha_qrInstance: chacha_qr
    port map
    (
        clk => hwclk,
        a => to_unsigned(1, 32),
        b => b,
        c => c,
        d => d,

        a2 => a2,
        b2 => b2,
        c2 => c2,
        d2 => d2,
        done => done
    );

    process (hwclk)
        variable state: unsigned(2 downto 0) := "000";
        variable counter: integer := 0;
    begin
        if rising_edge(hwclk) then
            ledGreen <= "0";
            cntr_9600 <= cntr_9600 + 1;
            cntr_32 <= cntr_32 + 1;

            if (cntr_9600 = period9600) then
                clk_9600 <= not clk_9600;
                cntr_9600 <= to_unsigned(0, 32);
            end if;

            --uart_txbyte <= to_unsigned(50, 8);
            if (txidleSignal = "1" and done = "1") then
                uart_txbyte <= "00110011";
            end if;

            if ((txDoneSignal = "1" or txidleSignal = "1") and done = "1") then
                uart_txbyte <= to_unsigned(138, 8);
                if (state = "000") then
                    led0 <= "0";
                    uart_txbyte <= a2(7 downto 0) xor b2(7 downto 0) xor c2(7 downto 0) xor d2(7 downto 0);
                    state := state + 1;
                    report "The value of 'uart_txbyte' is " & integer'image(to_integer(uart_txbyte));

                elsif (state = "001") then
                    uart_txbyte <= a2(15 downto 8) xor b2(15 downto 8) xor c2(15 downto 8) xor d2(15 downto 8);
                    state := state + 1;
                    report "The value of 'uart_txbyte' is " & integer'image(to_integer(uart_txbyte));

                elsif (state = "010") then
                    uart_txbyte <= a2(23 downto 16) xor b2(23 downto 16) xor c2(23 downto 16) xor d2(23 downto 16);
                    state := state + 1;
                    report "The value of 'uart_txbyte' is " & integer'image(to_integer(uart_txbyte));

                elsif (state = "011") then
                    uart_txbyte <= a2(31 downto 24) xor b2(31 downto 24) xor c2(31 downto 24) xor d2(31 downto 24);
                    state := "000";
                    report "The value of 'uart_txbyte' is " & integer'image(to_integer(uart_txbyte));
                    report "end" severity failure;
                end if;
            end if;
        end if;
    end process;

end test;

6/VHDL/uartTxTest/txTest/sim.vcd
$date
  Tue May 10 11:49:21 2022
$end
$version
  GHDL v0
$end
$timescale
  1 fs
$end
$scope module standard $end
$upscope $end
$scope module std_logic_1164 $end
$upscope $end
$scope module numeric_std $end
$upscope $end
$scope module uart8n1_tx2_tb $end
$var reg 1 ! ledgreen[0:0] $end
$var reg 1 " led0[0:0] $end
$var reg 1 # ftdi_tx[0:0] $end
$var reg 1 $ clk_9600 $end
$var reg 8 % uart_txbyte[7:0] $end
$var reg 1 & uart_send[0:0] $end
$var reg 1 ' uart_txed[0:0] $end
$var reg 1 ( uart_tx[0:0] $end
$var reg 32 ) cntr_9600[31:0] $end
$var reg 32 * period9600[31:0] $end
$var reg 32 + cntr_32[31:0] $end
$var reg 1 , txidlesignal[0:0] $end
$var reg 32 - a[31:0] $end
$var reg 32 . b[31:0] $end
$var reg 32 / c[31:0] $end
$var reg 32 0 d[31:0] $end
$var reg 32 1 a2[31:0] $end
$var reg 32 2 b2[31:0] $end
$var reg 32 3 c2[31:0] $end
$var reg 32 4 d2[31:0] $end
$var reg 1 5 done[0:0] $end
$var reg 1 6 txdonesignal[0:0] $end
$var reg 1 7 hwclk $end
$scope module uartinstance $end
$var reg 1 8 clk $end
$var reg 1 9 en[0:0] $end
$var reg 8 : txbyte[7:0] $end
$var reg 1 ; senddata[0:0] $end
$var reg 1 < isidle[0:0] $end
$var reg 1 = txdone[0:0] $end
$var reg 1 > tx[0:0] $end
$var reg 1 ? txbit[0:0] $end
$var reg 1 @ isidlesignal[0:0] $end
$var reg 1 A isdonesignal[0:0] $end
$upscope $end
$scope module chacha_qrinstance $end
$var reg 1 B clk $end
$var reg 32 C a[31:0] $end
$var reg 32 D b[31:0] $end
$var reg 32 E c[31:0] $end
$var reg 32 F d[31:0] $end
$var reg 32 G a2[31:0] $end
$var reg 32 H b2[31:0] $end
$var reg 32 I c2[31:0] $end
$var reg 32 J d2[31:0] $end
$var reg 1 K done[0:0] $end
$var reg 32 L a0signal[31:0] $end
$var reg 32 M b0signal[31:0] $end
$var reg 32 N c0signal[31:0] $end
$var reg 32 O d0signal[31:0] $end
$var reg 32 P a1signal[31:0] $end
$var reg 32 Q b1signal[31:0] $end
$var reg 32 R c1signal[31:0] $end
$var reg 32 S d1signal[31:0] $end
$var reg 32 T a2signal[31:0] $end
$var reg 32 U b2signal[31:0] $end
$var reg 32 V c2signal[31:0] $end
$var reg 32 W d2signal[31:0] $end
$var reg 32 X a3signal[31:0] $end
$var reg 32 Y b3signal[31:0] $end
$var reg 32 Z c3signal[31:0] $end
$var reg 32 [ d3signal[31:0] $end
$var reg 32 \ asignal[31:0] $end
$var reg 32 ] bsignal[31:0] $end
$var reg 32 ^ csignal[31:0] $end
$var reg 32 _ dsignal[31:0] $end
$upscope $end
$upscope $end
$enddefinitions $end
#0
bU !
bU "
b1 #
0$
b00000000 %
b0 &
b0 '
b0 (
b00000000000000000000000000000000 )
b00000000000000000000001001110001 *
b00000000000000000000000000000000 +
b1 ,
b00000000000000000000000000000000 -
b00000000000000000000000000000000 .
b00000000000000000000000000000000 /
b00000000000000000000000000000000 0
bUUUUUUUUUUUUUUUUUUUUUUUUUUUUUUUU 1
bUUUUUUUUUUUUUUUUUUUUUUUUUUUUUUUU 2
bUUUUUUUUUUUUUUUUUUUUUUUUUUUUUUUU 3
bUUUUUUUUUUUUUUUUUUUUUUUUUUUUUUUU 4
bU 5
b1 6
07
08
b1 9
b00000000 :
b1 ;
b1 <
b1 =
b1 >
b1 ?
b1 @
b1 A
0B
b00000000000000000000000000000001 C
b00000000000000000000000000000000 D
b00000000000000000000000000000000 E
b00000000000000000000000000000000 F
bUUUUUUUUUUUUUUUUUUUUUUUUUUUUUUUU G
bUUUUUUUUUUUUUUUUUUUUUUUUUUUUUUUU H
bUUUUUUUUUUUUUUUUUUUUUUUUUUUUUUUU I
bUUUUUUUUUUUUUUUUUUUUUUUUUUUUUUUU J
bU K
bUUUUUUUUUUUUUUUUUUUUUUUUUUUUUUUU L
bUUUUUUUUUUUUUUUUUUUUUUUUUUUUUUUU M
bUUUUUUUUUUUUUUUUUUUUUUUUUUUUUUUU N
bUUUUUUUUUUUUUUUUUUUUUUUUUUUUUUUU O
bUUUUUUUUUUUUUUUUUUUUUUUUUUUUUUUU P
bUUUUUUUUUUUUUUUUUUUUUUUUUUUUUUUU Q
bUUUUUUUUUUUUUUUUUUUUUUUUUUUUUUUU R
bUUUUUUUUUUUUUUUUUUUUUUUUUUUUUUUU S
bUUUUUUUUUUUUUUUUUUUUUUUUUUUUUUUU T
bUUUUUUUUUUUUUUUUUUUUUUUUUUUUUUUU U
bUUUUUUUUUUUUUUUUUUUUUUUUUUUUUUUU V
bUUUUUUUUUUUUUUUUUUUUUUUUUUUUUUUU W
bUUUUUUUUUUUUUUUUUUUUUUUUUUUUUUUU X
bUUUUUUUUUUUUUUUUUUUUUUUUUUUUUUUU Y
bUUUUUUUUUUUUUUUUUUUUUUUUUUUUUUUU Z
bUUUUUUUUUUUUUUUUUUUUUUUUUUUUUUUU [
bUUUUUUUUUUUUUUUUUUUUUUUUUUUUUUUU \
bUUUUUUUUUUUUUUUUUUUUUUUUUUUUUUUU ]
bUUUUUUUUUUUUUUUUUUUUUUUUUUUUUUUU ^
bUUUUUUUUUUUUUUUUUUUUUUUUUUUUUUUU _
#10000000
b0 !
b00000000000000000000000000000001 )
b00000000000000000000000000000001 +
b0 5
17
1B
b0 K
b00000000000000000000000000000001 L
b00000000000000000000000000000000 M
b00000000000000000000000000000000 N
b00000000000000010000000000000000 O
#20000000
07
0B
#30000000
b00000000000000000000000000000010 )
b00000000000000000000000000000010 +
17
1B
b00000000000000000000000000000001 P
b00010000000000000000000000000000 Q
b00000000000000010000000000000000 R
b00000000000000010000000000000000 S
#40000000
07
0B
#50000000
b00000000000000000000000000000011 )
b00000000000000000000000000000011 +
17
1B
b00010000000000000000000000000001 T
b00010000000000000000000000000000 U
b00000000000000010000000000000000 V
b00000001000000000000000100000000 W
#60000000
07
0B
#70000000
b00000000000000000000000000000100 )
b00000000000000000000000000000100 +
b1 5
17
1B
b1 K
b00010000000000000000000000000001 X
b10000000100000001000000000000000 Y
b00000001000000010000000100000000 Z
b00000001000000000000000100000000 [
#80000000
07
0B
#90000000
b0 "
b00110001 %
b00000000000000000000000000000101 )
b00000000000000000000000000000101 +
b0 5
17
b00110001 :
1B
b0 K
bXXXXXXXXXXXXXXXXXXXXXXXXXXXXXXXX L
bUUUUUUUUUUUUUUUUUUUUUUUUUUUUUUUU M
bUUUUUUUUUUUUUUUUUUUUUUUUUUUUUUUU N
bUUUUUUUUUUUUUUUU0000000000000000 O
#100000000
07
0B
#110000000
b00000000000000000000000000000110 )
b00000000000000000000000000000110 +
17
1B
bXXXXXXXXXXXXXXXXXXXXXXXXXXXXXXXX P
bUUUUUUUUUUUUUUUUUUUU000000000000 Q
bXXXXXXXXXXXXXXXXXXXXXXXXXXXXXXXX R
bUUUUUUUUUUUUUUUU0000000000000000 S
#120000000
07
0B
#130000000
b00000000000000000000000000000111 )
b00000000000000000000000000000111 +
17
1B
bXXXXXXXXXXXXXXXXXXXXXXXXXXXXXXXX T
bUUUUUUUUUUUUUUUUUUUU000000000000 U
bXXXXXXXXXXXXXXXXXXXXXXXXXXXXXXXX V
bUUUUUUUUXXXXXXXXXXXXXXXX00000000 W
#140000000
07
0B
#150000000
b00000000000000000000000000001000 )
b00000000000000000000000000001000 +
b00010000000000000000000000000001 1
b10000000100000001000000000000000 2
b00000001000000010000000100000000 3
b00000001000000000000000100000000 4
b1 5
17
1B
b00010000000000000000000000000001 G
b10000000100000001000000000000000 H
b00000001000000010000000100000000 I
b00000001000000000000000100000000 J
b1 K
bXXXXXXXXXXXXXXXXXXXXXXXXXXXXXXXX X
bUUUUUUUUUUUUUXXXXXXXXXXXX0000000 Y
bXXXXXXXXXXXXXXXXXXXXXXXXXXXXXXXX Z
bUUUUUUUUXXXXXXXXXXXXXXXX00000000 [
b00010000000000000000000000000001 \
b10000000100000001000000000000000 ]
b00000001000000010000000100000000 ^
b00000001000000000000000100000000 _
#160000000
07
0B
#170000000
b00110010 %
b00000000000000000000000000001001 )
b00000000000000000000000000001001 +
b0 5
17
b00110010 :
1B
b0 K
b10010000100000001000000000000001 L
b10000000100000001000000000000000 M
b00000001000000010000000100000000 N
b10000001000000010000000000000000 O
#180000000
07
0B
#190000000
b00000000000000000000000000001010 )
b00000000000000000000000000001010 +
17
1B
b10010000100000001000000000000001 P
b00101000000100000000000000000000 Q
b10000010000000100000000100000000 R
b10000001000000010000000000000000 S
#200000000
07
0B
#210000000
b00000000000000000000000000001011 )
b00000000000000000000000000001011 +
17
1B
b10111000100100001000000000000001 T
b00101000000100000000000000000000 U
b10000010000000100000000100000000 V
b10010001100000000000000100000000 W
#220000000
07
0B
#230000000
b00000000000000000000000000001100 )
b00000000000000000000000000001100 +
bXXXXXXXXXXXXXXXXXXXXXXXXXXXXXXXX 1
bUUUUUUUUUUUUUXXXXXXXXXXXX0000000 2
bXXXXXXXXXXXXXXXXXXXXXXXXXXXXXXXX 3
bUUUUUUUUXXXXXXXXXXXXXXXX00000000 4
b1 5
17
1B
bXXXXXXXXXXXXXXXXXXXXXXXXXXXXXXXX G
bUUUUUUUUUUUUUXXXXXXXXXXXX0000000 H
bXXXXXXXXXXXXXXXXXXXXXXXXXXXXXXXX I
bUUUUUUUUXXXXXXXXXXXXXXXX00000000 J
b1 K
b10111000100100001000000000000001 X
b11001001000000010000000000000000 Y
b00010011100000100000001000000000 Z
b10010001100000000000000100000000 [
bXXXXXXXXXXXXXXXXXXXXXXXXXXXXXXXX \
bUUUUUUUUUUUUUXXXXXXXXXXXX0000000 ]
bXXXXXXXXXXXXXXXXXXXXXXXXXXXXXXXX ^
bUUUUUUUUXXXXXXXXXXXXXXXX00000000 _
#240000000
07
0B
#250000000
b00110011 %
b00000000000000000000000000001101 )
b00000000000000000000000000001101 +
b0 5
17
b00110011 :
1B
b0 K
bXXXXXXXXXXXXXXXXXXXXXXXXXXXXXXXX L
bUUUUUUUUUUUUUXXXXXXXXXXXX0000000 M
bXXXXXXXXXXXXXXXXXXXXXXXXXXXXXXXX N
bXXXXXXXXXXXXXXXX0000000000000000 O
#260000000
07
0B
#270000000
b00000000000000000000000000001110 )
b00000000000000000000000000001110 +
17
1B
bXXXXXXXXXXXXXXXXXXXXXXXXXXXXXXXX P
bUXXXXXXXXXXXXXXXXXXX000000000000 Q
bXXXXXXXXXXXXXXXXXXXXXXXXXXXXXXXX R
bXXXXXXXXXXXXXXXX0000000000000000 S
#280000000
07
0B
#290000000
b00000000000000000000000000001111 )
b00000000000000000000000000001111 +
17
1B
bXXXXXXXXXXXXXXXXXXXXXXXXXXXXXXXX T
bUXXXXXXXXXXXXXXXXXXX000000000000 U
bXXXXXXXXXXXXXXXXXXXXXXXXXXXXXXXX V
bXXXXXXXXXXXXXXXXXXXXXXXX00000000 W
#300000000
07
0B
#310000000
b00000000000000000000000000010000 )
b00000000000000000000000000010000 +
b10111000100100001000000000000001 1
b11001001000000010000000000000000 2
b00010011100000100000001000000000 3
b10010001100000000000000100000000 4
b1 5
17
1B
b10111000100100001000000000000001 G
b11001001000000010000000000000000 H
b00010011100000100000001000000000 I
b10010001100000000000000100000000 J
b1 K
bXXXXXXXXXXXXXXXXXXXXXXXXXXXXXXXX X
bXXXXXXXXXXXXXXXXXXXXXXXXX0000000 Y
bXXXXXXXXXXXXXXXXXXXXXXXXXXXXXXXX Z
bXXXXXXXXXXXXXXXXXXXXXXXX00000000 [
b10111000100100001000000000000001 \
b11001001000000010000000000000000 ]
b00010011100000100000001000000000 ^
b10010001100000000000000100000000 _
